taha.py
taha-3.0.1.dist-info/METADATA
taha-3.0.1.dist-info/WHEEL
taha-3.0.1.dist-info/top_level.txt
taha-3.0.1.dist-info/RECORD
