Metadata-Version: 2.4
Name: taha
Version: 3.0.1
Summary: 📦 Taha Library - Premium Edition: کتابخانه چندمنظوره فارسی با قابلیت‌های صوتی، هوش مصنوعی، گرافیکی و ابزارهای کاربردی
Author: Taha (NS-TAHA1515)
Keywords: taha library persian voice tts speech recognition ai turtle pygame tools premium فارسی صوتی هوش-مصنوعی کتابخانه
Classifier: Programming Language :: Python :: 3
Classifier: Programming Language :: Python :: 3.8
Classifier: Programming Language :: Python :: 3.9
Classifier: Programming Language :: Python :: 3.10
Classifier: Programming Language :: Python :: 3.11
Classifier: Programming Language :: Python :: 3.12
Classifier: Programming Language :: Python :: 3.13
Classifier: License :: Other/Proprietary License
Classifier: Operating System :: OS Independent
Classifier: Intended Audience :: Developers
Classifier: Topic :: Software Development :: Libraries :: Python Modules
Classifier: Natural Language :: Persian
Requires-Python: >=3.8
Requires-Dist: pygame
Requires-Dist: requests
Requires-Dist: pyttsx3
Requires-Dist: pyperclip
Requires-Dist: Pillow
Requires-Dist: SpeechRecognition
Requires-Dist: cryptography
Requires-Dist: transformers
Requires-Dist: psutil
Requires-Dist: pytz
Requires-Dist: PyJWT
Requires-Dist: beautifulsoup4
Requires-Dist: pyautogui
Requires-Dist: gTTS
Provides-Extra: dev
Requires-Dist: build; extra == "dev"
Requires-Dist: twine; extra == "dev"
Requires-Dist: wheel; extra == "dev"
Dynamic: author
Dynamic: classifier
Dynamic: description
Dynamic: description-content-type
Dynamic: keywords
Dynamic: provides-extra
Dynamic: requires-dist
Dynamic: requires-python
Dynamic: summary
